{
	"pattrstorage" : 	{
		"name" : "transient_crossfade_parameters[1]",
		"slots" : 		{
			"1" : 			{
				"id" : 1,
				"data" : 				{
					"transient_helper" : [ 1 ],
					"env_decay" : [ 393.451705391850737 ],
					"noise_gate" : [ 0.051090245500513 ],
					"interpolate_crossfades" : [ 71.0 ],
					"env_attack" : [ 8.0 ],
					"lock_low_mod" : [ 0 ],
					"lock_very_low_mod" : [ 0 ],
					"low_crossfade_offset" : [ 40.157480314960559 ],
					"crossfade_env_sens" : [ 1.758786766504442 ],
					"mix_env_logic::env_bottom" : [ 0.0 ],
					"mix_env_logic::env_top" : [ 100.0 ],
					"mix_env_logic::easing_function" : [ 3 ],
					"mix_env_logic::invert" : [ 1 ]
				}

			}

		}

	}

}
